ash_utils/__init__.py
ash_utils/constants.py
ash_utils/apis/__init__.py
ash_utils/apis/base_api.py
ash_utils/healthcheck/__init__.py
ash_utils/healthcheck/utils.py
ash_utils/integrations/__init__.py
ash_utils/integrations/constants.py
ash_utils/integrations/sentry.py
ash_utils/middlewares/__init__.py
ash_utils/middlewares/catch_unexpected_exception.py
ash_utils/middlewares/permissions_policy.py
ash_utils/middlewares/request_id.py
ash_utils/middlewares/security.py
ash_utils/support/__init__.py
ash_utils/support/ticket.py
ashwelness_utils-0.4.2.dist-info/METADATA
ashwelness_utils-0.4.2.dist-info/WHEEL
ashwelness_utils-0.4.2.dist-info/RECORD
