Metadata-Version: 2.4
Name: ashwelness-utils
Version: 0.4.2
Summary: Python library containing common utilities used across various ASH projects.
Author-email: Shakun Raman <shakunroman@gmail.com>
Keywords: fastapi,integrations,middleware,security,sentry,utilities
Requires-Python: <4.0,>=3.11
Requires-Dist: fastapi>=0.115.7
Requires-Dist: httpx>=0.28.1
Requires-Dist: loguru>=0.7.3
Requires-Dist: nested-lookup>=0.2.25
Requires-Dist: pydantic<3.0.0,>=2.0.0
Requires-Dist: secweb>=1.18.1
Requires-Dist: sentry-sdk>=2.22.0
